[{"month": "2023-01", "unique_tags": 19072}, {"month": "2023-02", "unique_tags": 18345}, {"month": "2023-03", "unique_tags": 18674}, {"month": "2023-04", "unique_tags": 17063}, {"month": "2023-05", "unique_tags": 16890}, {"month": "2023-06", "unique_tags": 16839}, {"month": "2023-07", "unique_tags": 16543}, {"month": "2023-08", "unique_tags": 16422}, {"month": "2023-09", "unique_tags": 15484}, {"month": "2023-10", "unique_tags": 15586}, {"month": "2023-11", "unique_tags": 15433}, {"month": "2023-12", "unique_tags": 14154}, {"month": "2024-01", "unique_tags": 15062}, {"month": "2024-02", "unique_tags": 14939}, {"month": "2024-03", "unique_tags": 15099}, {"month": "2024-04", "unique_tags": 17245}, {"month": "2024-05", "unique_tags": 16897}, {"month": "2024-06", "unique_tags": 15100}, {"month": "2024-07", "unique_tags": 15138}, {"month": "2024-08", "unique_tags": 14011}, {"month": "2024-09", "unique_tags": 13280}, {"month": "2024-10", "unique_tags": 13048}, {"month": "2024-11", "unique_tags": 12220}, {"month": "2024-12", "unique_tags": 11467}, {"month": "2025-01", "unique_tags": 11508}, {"month": "2025-02", "unique_tags": 10828}, {"month": "2025-03", "unique_tags": 11392}, {"month": "2025-04", "unique_tags": 2210}]